data/__init__.py
errors/__init__.py
future/__init__.py
future/tqdm/__init__.py
future/tqdm/__main__.py
future/tqdm/_dist_ver.py
future/tqdm/_main.py
future/tqdm/_monitor.py
future/tqdm/_tqdm.py
future/tqdm/_tqdm_gui.py
future/tqdm/_tqdm_notebook.py
future/tqdm/_tqdm_pandas.py
future/tqdm/_utils.py
future/tqdm/asyncio.py
future/tqdm/auto.py
future/tqdm/autonotebook.py
future/tqdm/cli.py
future/tqdm/dask.py
future/tqdm/gui.py
future/tqdm/keras.py
future/tqdm/notebook.py
future/tqdm/rich.py
future/tqdm/std.py
future/tqdm/tk.py
future/tqdm/utils.py
future/tqdm/version.py
future/tqdm/contrib/__init__.py
future/tqdm/contrib/bells.py
future/tqdm/contrib/concurrent.py
future/tqdm/contrib/discord.py
future/tqdm/contrib/itertools.py
future/tqdm/contrib/telegram.py
future/tqdm/contrib/utils_worker.py
logger/__init__.py
templates/__init__.py
templates/simple.py
tests/__init__.py
tests/data/__init__.py
tests/data/test_Data.py
tests/errors/__init__.py
tests/errors/test_errors.py
tests/logger/__init__.py
tests/logger/test_logger.py
tests/templates/__init__.py
tests/templates/test_simple.py
tests/templates/test_templates.py
reportio-0.3.5.dist-info/LICENSE.txt
reportio-0.3.5.dist-info/METADATA
reportio-0.3.5.dist-info/WHEEL
reportio-0.3.5.dist-info/top_level.txt
reportio-0.3.5.dist-info/RECORD
