Metadata-Version: 2.1
Name: reportio
Version: 0.3.5
Summary: A package containing templates for reporting with Python.
Home-page: https://github.com/deschman/reportio
Author: Dan Eschman
Author-email: deschman007@gmail.com
License: UNKNOWN
Platform: UNKNOWN
Classifier: Natural Language :: English
Classifier: Topic :: Software Development :: Libraries :: Python Modules
Classifier: Programming Language :: Python :: 3
Classifier: Operating System :: Microsoft :: Windows
Classifier: Development Status :: 3 - Alpha
Classifier: License :: OSI Approved :: GNU General Public License v3 (GPLv3)
Requires-Python: >=3.3
Requires-Dist: pysqlite3
Requires-Dist: numba
Requires-Dist: pytest-dbfixtures
Requires-Dist: pytest
Requires-Dist: pandas
Requires-Dist: pyarrow
Requires-Dist: openpyxl
Provides-Extra: gzip_alt_processing
Requires-Dist: fastparquet ; extra == 'gzip_alt_processing'
Provides-Extra: jdbc
Requires-Dist: jaydebeapi ; extra == 'jdbc'
Provides-Extra: multithread_support
Requires-Dist: dask ; extra == 'multithread_support'
Provides-Extra: mysql_support
Requires-Dist: mysql-connector-python ; extra == 'mysql_support'
Provides-Extra: odbc
Requires-Dist: pyodbc ; extra == 'odbc'
Provides-Extra: progress_bar
Requires-Dist: tqdm ; extra == 'progress_bar'
